MANIFEST.in
setup.cfg
setup.py
config/VERSION
config/requirements.txt
twentyc.tools.egg-info/PKG-INFO
twentyc.tools.egg-info/SOURCES.txt
twentyc.tools.egg-info/dependency_links.txt
twentyc.tools.egg-info/namespace_packages.txt
twentyc.tools.egg-info/not-zip-safe
twentyc.tools.egg-info/requires.txt
twentyc.tools.egg-info/top_level.txt
twentyc/tools/CryptoUtil.py
twentyc/tools/__init__.py
twentyc/tools/cli.py
twentyc/tools/config.py
twentyc/tools/constants.py
twentyc/tools/session.py
twentyc/tools/syslogfix.py
twentyc/tools/tests.py
twentyc/tools/thread.py