Metadata-Version: 1.1
Name: twentyc.tools
Version: 0.1.6
Summary: various python tool libraries / helpers
Home-page: https://github.com/20c/twentyc.tools
Author: Twentieth Century
Author-email: code@20c.com
License: UNKNOWN
Download-URL: https://github.com/20c/twentyc.tools/tarball/0.1.6
Platform: UNKNOWN
Classifier: Development Status :: 4 - Beta
Classifier: Intended Audience :: Developers
Classifier: License :: OSI Approved :: Apache Software License
Classifier: Topic :: Software Development :: Libraries :: Python Modules
